AUTHORS.rst
CONTRIBUTING.rst
HISTORY.rst
LICENSE
MANIFEST.in
README.rst
setup.cfg
setup.py
docs/Makefile
docs/authors.rst
docs/conf.py
docs/contributing.rst
docs/history.rst
docs/index.rst
docs/installation.rst
docs/make.bat
docs/readme.rst
docs/usage.rst
pynamics365/__init__.py
pynamics365/auth.py
pynamics365/pynamics365.py
pynamics365.egg-info/PKG-INFO
pynamics365.egg-info/SOURCES.txt
pynamics365.egg-info/dependency_links.txt
pynamics365.egg-info/not-zip-safe
pynamics365.egg-info/requires.txt
pynamics365.egg-info/top_level.txt
tests/__init__.py
tests/test_pynamics365.py