Metadata-Version: 1.1
Name: pynamics365
Version: 0.1.0
Summary: Python 3 connector to Dymanics 365 CRM
Home-page: https://github.com/DeastinY/pynamics365
Author: Richard Polzin
Author-email: polzin.richard@gmail.com
License: MIT license
Keywords: pynamics365
Platform: UNKNOWN
Classifier: Development Status :: 2 - Pre-Alpha
Classifier: Intended Audience :: Developers
Classifier: License :: OSI Approved :: MIT License
Classifier: Natural Language :: English
Classifier: Programming Language :: Python :: 2
Classifier: Programming Language :: Python :: 2.6
Classifier: Programming Language :: Python :: 2.7
Classifier: Programming Language :: Python :: 3
Classifier: Programming Language :: Python :: 3.3
Classifier: Programming Language :: Python :: 3.4
Classifier: Programming Language :: Python :: 3.5
